odoo/addons/event_registration_partner_unique/README.rst
odoo/addons/event_registration_partner_unique/__init__.py
odoo/addons/event_registration_partner_unique/__manifest__.py
odoo/addons/event_registration_partner_unique/i18n/ca.po
odoo/addons/event_registration_partner_unique/i18n/es.po
odoo/addons/event_registration_partner_unique/i18n/event_registration_partner_unique.pot
odoo/addons/event_registration_partner_unique/i18n/fr.po
odoo/addons/event_registration_partner_unique/i18n/it.po
odoo/addons/event_registration_partner_unique/models/__init__.py
odoo/addons/event_registration_partner_unique/models/event.py
odoo/addons/event_registration_partner_unique/readme/CONTRIBUTORS.md
odoo/addons/event_registration_partner_unique/readme/DESCRIPTION.md
odoo/addons/event_registration_partner_unique/readme/ROADMAP.md
odoo/addons/event_registration_partner_unique/readme/USAGE.md
odoo/addons/event_registration_partner_unique/static/description/icon.png
odoo/addons/event_registration_partner_unique/static/description/index.html
odoo/addons/event_registration_partner_unique/tests/__init__.py
odoo/addons/event_registration_partner_unique/tests/test_event.py
odoo/addons/event_registration_partner_unique/views/event_event_view.xml
odoo_addon_event_registration_partner_unique-18.0.1.0.0.4.dist-info/METADATA
odoo_addon_event_registration_partner_unique-18.0.1.0.0.4.dist-info/WHEEL
odoo_addon_event_registration_partner_unique-18.0.1.0.0.4.dist-info/top_level.txt
odoo_addon_event_registration_partner_unique-18.0.1.0.0.4.dist-info/RECORD
